[
    {
        "result": "Incorrect",
        "path": "20220602020",
        "runOutput": "Hello, World! C \n",
        "expectedOutput": "Hello, Sinem! C \n"
    },
    {
        "result": "Incorrect",
        "path": "20220602020",
        "runOutput": "Compile error: No .java file found in C:\\Users\\Sinem\\Desktop\\C\\20220602020",
        "expectedOutput": "Compile error: No .java file found in C:\\Users\\Sinem\\Desktop\\outcome_c"
    },
    {
        "result": "Incorrect",
        "path": "20220602020",
        "runOutput": "Hello, World! C \n",
        "expectedOutput": "Hello, Sinem! C \n"
    }
]